[
  {
    "index": 4,
    "title": "dGame",
    "description": "Multiplayer Doodle Game.",
    "live": "https://dgame.vercel.app/",
    "github": "https://github.com/Shubham-Rasal/wec22-multiplayer-game",
    "active": true
  },
  {
    "index": 5,
    "title": "iNeural",
    "description": "A simple neural network library built from scratch in javascript.",
    "github": "https://github.com/Shubham-Rasal/iNeural",
    "active": true
  },
  {
    "index": 6,
    "title": "Perceptron",
    "description": "Visualise a single layer perceptron.",
    "live": "https://shubham-rasal.github.io/Perceptron/",
    "github": "https://github.com/Shubham-Rasal/Perceptron",
    "active": true
  },
  {
    "index": 8,
    "title": "Flow Forge",
    "description": "Automation Planner",
    "live": "https://flowforge.vercel.app/",
    "github": "https://github.com/Shubham-Rasal/flow-forge",
    "active": true
  },
  {
    "index": 1,
    "title": "Harveeco",
    "description": "A Farmer's DataDAO. A decentralised application for farmers to store and share their data.",
    "live": "https://harveeco.vercel.app/",
    "github": "https://github.com/Shubham-Rasal/Deano",
    "active": false
  },
  {
    "index": 2,
    "title": "Deano",
    "description": "Decentralised Annotation Network.",
    "live": "https://deano.vercel.app/",
    "github": "https://github.com/Shubham-Rasal/Deano",
    "active": false
  },
  {
    "index": 3,
    "title": "Mindful AI",
    "description": "Mental Illness Detection using AI.",
    "live": "https://app.supademo.com/demo/2XthgTOFVJYIYPVHqjCtK",
    "github": "https://github.com/Shubham-Rasal/Mindful-AI",
    "active": false
  },
  {
    "index": 7,
    "title": "CipherCraft",
    "description": "A Decentralised Hub for federated model training on access controlled private datasets.",
    "live": "https://ethglobal.com/showcase/ciphercraft-3g8kp",
    "github": "https://github.com/Shubham-Rasal/CipherCraft",
    "active": false
  },
  {
    "index": 8,
    "title": "SMEasy",
    "description": "Automatic Government Scheme Recommendation and AI based Loan Approval",
    "live": "https://smeasy.vercel.app/",
    "github": "https://github.com/Shubham-Rasal/SMEasy",
    "active": false
  }
]
